olea/__init__.py
olea/analysis/__init__.py
olea/analysis/analysis.py
olea/analysis/cold.py
olea/analysis/generic.py
olea/analysis/hatecheck.py
olea/analysis/generic-unused/__init__.py
olea/analysis/generic-unused/search_regex.py
olea/analysis/generic-unused/search_substring.py
olea/base/__init__.py
olea/data/__init__.py
olea/data/cold.py
olea/data/dataset.py
olea/data/dso.py
olea/data/hatecheck.py
olea/data/hatexplain.py
olea/experiments/__init__.py
olea/experiments/data_mocker.py
olea/experiments/usecases.py
olea/metrics/__init__.py
olea/metrics/metrics.py
olea/unittests/__init__.py
olea/unittests/functionalities.py
olea/utils/__init__.py
olea/utils/analysis_tools.py
olea/utils/preprocess_text.py
olea/utils/twitteraae/__init__.py
olea/utils/twitteraae/code/__init__.py
olea/utils/twitteraae/code/detection.py
olea/utils/twitteraae/code/emoji.py
olea/utils/twitteraae/code/predict.py
olea/utils/twitteraae/code/twokenize.py
olea/utils/twitteraae/model/model_count_table.txt
olea/utils/twitteraae/model/model_vocab.txt
olea/viz/__init__.py
olea/viz/viz.py
olea-0.1.0.dist-info/METADATA
olea-0.1.0.dist-info/WHEEL
olea-0.1.0.dist-info/top_level.txt
olea-0.1.0.dist-info/RECORD
