Metadata-Version: 2.1
Name: olea
Version: 0.1.0
Summary: OLEA (Offensive Language Error Analysis) is an open source library for diagnostic evaluation and error analysis of models for offensive language detection.
Author: OLEA Team, Anonymized for Review
Author-email: <olea.ask@gmail.com>
License: UNKNOWN
Keywords: python,linguistics,linguistic-analysis
Platform: UNKNOWN
Classifier: Development Status :: 3 - Alpha
Classifier: Intended Audience :: Education
Classifier: Programming Language :: Python :: 3
Classifier: Operating System :: MacOS :: MacOS X
Classifier: Operating System :: Microsoft :: Windows
Requires-Dist: numpy (>1.21.0)
Requires-Dist: scipy (>1.6.0)
Requires-Dist: datasets (>2.2.0)
Requires-Dist: matplotlib (>3.0)
Requires-Dist: pandas (>1.2.0)
Requires-Dist: Pillow (>8.0.0)
Requires-Dist: scikit-learn (>1.0)
Requires-Dist: emoji (>1.0)
Requires-Dist: wordsegment (>1.3)
